wtform_address.py
wtform_address-0.1.1.dist-info/LICENSE
wtform_address-0.1.1.dist-info/METADATA
wtform_address-0.1.1.dist-info/WHEEL
wtform_address-0.1.1.dist-info/top_level.txt
wtform_address-0.1.1.dist-info/RECORD
