Metadata-Version: 2.1
Name: wtform-address
Version: 0.1.1
Summary: Physical address fields (CountrySelectField, StateSelectField) for wtform
Home-page: https://github.com/samos123/wtform-address
Author: Sam Stoelinga
License-File: LICENSE
Requires-Dist: pycountry
Requires-Dist: wtform
